{"operations":[{"i":-1,"o":1,"p":{"01621fb84e320000f001":"public","01703376c4a81c0e9d94":"stable","fdff023000000000000011":"Get From JSON 2","ff023000000000000011":"Get From JSON 2","v":11},"t":"017fb1d884849d21956c"},{"i":-1,"o":1,"p":{"01703376c4a81c0e9d91":"Enables to extract the values from json by two paths","01703376c4a81c0e9d92":"Extracts the object or primitive from json by two paths.\n\nThe path is specified in dotted form. To extract an element inside an array, the property needs to be included inside brackets, e.g. '[name]'.\n\nExamples\n----------------\n```\nGetFromJSON({ \"a\": { \"b\": \"hello\"}}, 'a.b') -> \"hello\"\nGetFromJSON({ \"a\": [ { \"b\": \"hello\", \"c\": \"boo 1\" }, { \"b\": \"coucou\" , \"c\": \"boo 2\" }] } , 'a.[b]') -> [\"hello\",\"coucou\"]\nGetFromJSON({  \"a\": [ { \"b\": { \"c\": \"boo 1\" } }, { \"b\": { \"c\": \"boo 2\" } } ] } , 'a.[b].c') -> [\"boo 1\",\"boo 2\"]\n```\n\nFull doc of the syntax supported: [jsonpath-plus](https://www.npmjs.com/package/jsonpath-plus). \n\nA list will be returned having multiple results found.\n\nIf the path was not found the result of the related output would be null. \nIf one of the paths was not found Error Flow would be triggered.","v":234},"t":"017fb1d8a43948985fd3"},{"i":-1,"o":1,"p":{"v":1},"t":"017fb1d8b3ae882ed2c9"},{"i":-1,"o":1,"p":{"01740c5d4ae4b520dd01":0,"ff023000000000000011":"Source","v":11},"t":"017fb1d8b3ae8bde3f41"},{"i":-1,"o":1,"p":{"ff023000000000000011":"Descender output","v":1},"t":"017fb1d8b3af56ffa2aa"},{"i":-1,"o":1,"p":{"01703376c4a81c0e9d92":"The JSON object or string to find from","v":74},"t":"017fb1d8b43e0447ce61"},{"i":-1,"o":1,"p":{"v":1},"t":"017fb1d8b5c2367e3828"},{"i":-1,"o":1,"p":{"ff023000000000000011":"Descender output","v":1},"t":"017fb1d8b5c267cbe36b"},{"i":-1,"o":1,"p":{"01740c5d4ae4b520dd01":1,"ff023000000000000011":"Path1","v":7},"t":"017fb1d8b5c2e4667fc7"},{"i":-1,"o":1,"p":{"01703376c4a81c0e9d92":"The property path","v":57},"t":"017fb1d8b64d32ee222d"},{"i":-1,"o":1,"p":{"01740c5d4ae4b520dd01":0,"ff023000000000000011":"Value1","v":5},"t":"017fb1d8bc2632aee8a3"},{"i":-1,"o":1,"p":{"ff023000000000000011":"Ascender input","v":1},"t":"017fb1d8bc265473dbfa"},{"i":-1,"o":1,"p":{"v":1},"t":"017fb1d8bc269b9159e9"},{"i":-1,"o":1,"p":{"01703376c4a81c0e9d92":"The object or primitive found by Path1","v":81},"t":"017fb1d8bcbbb8748839"},{"i":-1,"o":1,"p":{"01740c5d4ae4b520dd01":1,"ff023000000000000011":"Value2","v":1},"t":"017fb1e4ee510c07892c"},{"i":-1,"o":1,"p":{"v":1},"t":"017fb1e4ee5184e2eb63"},{"i":-1,"o":1,"p":{"ff023000000000000011":"Ascender input","v":1},"t":"017fb1e4ee51a0586e51"},{"i":-1,"o":1,"p":{"01703376c4a81c0e9d92":"The object or primitive found by Path2","v":5},"t":"017fb1e54bf72bcb4b8e"},{"i":-1,"o":1,"p":{"01740c5d4ae4b520dd01":2,"ff023000000000000011":"Path2","v":5},"t":"017fb1e57a662def01d6"},{"i":-1,"o":1,"p":{"ff023000000000000011":"Descender output","v":1},"t":"017fb1e57a66419a0f29"},{"i":-1,"o":1,"p":{"v":1},"t":"017fb1e57a66f894c470"},{"i":-1,"o":1,"p":{"01703376c4a81c0e9d92":"The property path","v":3},"t":"017fb1e57b9c71bf9fc1"},{"i":-1,"o":1,"p":{"v":1},"t":"017fb221b0488673e342"},{"i":-1,"o":1,"p":{"01621f6ab58c2f884654":20401,"01621f6ab6ac89348f20":19936,"v":168},"t":"017fb221b048e4653137"},{"i":-1,"o":1,"p":{"v":1},"t":"017fb221b4da5a1d4418"},{"i":-1,"o":1,"p":{"01621f6ab58c2f884654":20399,"01621f6ab6ac89348f20":20080,"v":247},"t":"017fb221b4dac09ceb78"},{"i":-1,"o":1,"p":{"ff023000000000000011":"Ascender input","v":1},"t":"017fb222043104ba27ee"},{"i":-1,"o":1,"p":{"v":1},"t":"017fb22204311b611435"},{"i":-1,"o":1,"p":{"01740c5d4ae4b520dd01":2,"ff023000000000000011":"Error Flow","v":1},"t":"017fb2220431e8e2bad4"},{"i":-1,"o":1,"p":{"01621f6ab58c2f884654":20800,"01621f6ab6ac89348f20":20186,"v":720},"t":"017fb222223f390dd268"},{"i":-1,"o":1,"p":{"v":1},"t":"017fb222223f5ac1f6f7"},{"i":-1,"o":1,"p":{"v":1},"t":"017fb2222ffa8cb78be2"},{"i":-1,"o":1,"p":{"v":1},"t":"017fb22236e92322885b"},{"i":-1,"o":1,"p":{"v":1},"t":"017fb22247831023ae72"},{"i":-1,"o":1,"p":{"v":1},"t":"017fb261198fa4b943e8"},{"i":-1,"o":1,"p":{"v":1},"t":"017fb2611feeced55b48"},{"i":-1,"o":1,"p":{"v":1},"t":"017fb26124fd65f12ba2"},{"i":-1,"o":1,"p":{"v":1},"t":"017fb2612b1a9ecb6e39"},{"i":-1,"o":1,"p":{"v":1},"t":"017fb261576a7a63890c"},{"i":-1,"o":1,"p":{"v":1},"t":"017fb2615f7086c2ffb6"},{"i":-1,"o":1,"p":{"v":1},"t":"017fb34fd9db5f807a50"}],"optionalOperations":[],"rootTag":"017fb1d884849d21956c"}
