{"operations":[{"i":-1,"o":1,"p":{"ff023000000000000011":"Ascender input","v":1},"t":"017cef8a4cba09a45624"},{"i":-1,"o":1,"p":{"v":1},"t":"017cef8a4cba0d60ead5"},{"i":-1,"o":1,"p":{"01621f6ab58c2f884654":20750,"01621f6ab6ac89348f20":20450,"v":1},"t":"017cef8a4cba0d775302"},{"i":-1,"o":1,"p":{"v":1},"t":"017cef8a4cba0f712667"},{"i":-1,"o":1,"p":{"v":1},"t":"017cef8a4cba107ba68d"},{"i":-1,"o":1,"p":{"01740c5d4ae4b520dd01":0,"ff023000000000000011":"Control Flow","v":1},"t":"017cef8a4cba14e37622"},{"i":-1,"o":1,"p":{"01740c5d4ae4b520dd01":2,"ff023000000000000011":"Error Flow","v":1},"t":"017cef8a4cba17f6d876"},{"i":-1,"o":1,"p":{"01740c5d4ae4b520dd01":3,"ff023000000000000011":"Body","v":1},"t":"017cef8a4cba1f65c72f"},{"i":-1,"o":1,"p":{"ff023000000000000011":"Ascender input","v":1},"t":"017cef8a4cba21f13d2e"},{"i":-1,"o":1,"p":{"ff023000000000000011":"Descender output","v":1},"t":"017cef8a4cba28323b5c"},{"i":-1,"o":1,"p":{"01621f6ab58c2f884654":21000,"01621f6ab6ac89348f20":20600,"v":1},"t":"017cef8a4cba2937fc9f"},{"i":-1,"o":1,"p":{"v":1},"t":"017cef8a4cba2df3367a"},{"i":-1,"o":1,"p":{"v":1},"t":"017cef8a4cba343f0ee0"},{"i":-1,"o":1,"p":{"ff023000000000000011":"Ascender input","v":1},"t":"017cef8a4cba34dfe6fe"},{"i":-1,"o":1,"p":{"v":1},"t":"017cef8a4cba38873dbc"},{"i":-1,"o":1,"p":{"01740c5d4ae4b520dd01":2,"ff023000000000000011":"BatchIdentifyingPlant","v":1},"t":"017cef8a4cba3a9be1fb"},{"i":-1,"o":1,"p":{"v":1},"t":"017cef8a4cba3de18f9c"},{"i":-1,"o":1,"p":{"v":1},"t":"017cef8a4cba430d5627"},{"i":-1,"o":1,"p":{"v":1},"t":"017cef8a4cba46022ee0"},{"i":-1,"o":1,"p":{"v":1},"t":"017cef8a4cba49a8673c"},{"i":-1,"o":1,"p":{"v":1},"t":"017cef8a4cba4aaf68bc"},{"i":-1,"o":1,"p":{"v":1},"t":"017cef8a4cba4b3703f8"},{"i":-1,"o":1,"p":{"v":1},"t":"017cef8a4cba4d2a0a63"},{"i":-1,"o":1,"p":{"01621f6ab58c2f884654":20000,"01621f6ab6ac89348f20":20000,"v":1},"t":"017cef8a4cba52bd9574"},{"i":-1,"o":1,"p":{"01621f6ab58c2f884654":22250,"01621f6ab6ac89348f20":21350,"v":1},"t":"017cef8a4cba550ef641"},{"i":-1,"o":1,"p":{"01740c5d4ae4b520dd01":1,"ff023000000000000011":"Material","v":1},"t":"017cef8a4cba5603c461"},{"i":-1,"o":1,"p":{"v":1},"t":"017cef8a4cba5b524bfd"},{"i":-1,"o":1,"p":{"v":1},"t":"017cef8a4cba5b71fc35"},{"i":-1,"o":1,"p":{"v":1},"t":"017cef8a4cba5c09cc8d"},{"i":-1,"o":1,"p":{"v":1},"t":"017cef8a4cba5e26a5db"},{"i":-1,"o":1,"p":{"01621f6ab58c2f884654":21750,"01621f6ab6ac89348f20":21050,"v":1},"t":"017cef8a4cba60339993"},{"i":-1,"o":1,"p":{"ff023000000000000011":"Descender output","v":1},"t":"017cef8a4cba6608582f"},{"i":-1,"o":1,"p":{"v":1},"t":"017cef8a4cba697a3984"},{"i":-1,"o":1,"p":{"01621f6ab58c2f884654":22750,"01621f6ab6ac89348f20":21650,"v":1},"t":"017cef8a4cba6cdfa3cd"},{"i":-1,"o":1,"p":{"01621f6ab58c2f884654":20250,"01621f6ab6ac89348f20":20150,"v":1},"t":"017cef8a4cba6f863d2e"},{"i":-1,"o":1,"p":{"v":1},"t":"017cef8a4cba77a13144"},{"i":-1,"o":1,"p":{"v":1},"t":"017cef8a4cba7b316319"},{"i":-1,"o":1,"p":{"v":1},"t":"017cef8a4cba7b9904ad"},{"i":-1,"o":1,"p":{"01621f6ab58c2f884654":21250,"01621f6ab6ac89348f20":20750,"v":1},"t":"017cef8a4cba7e1cecc7"},{"i":-1,"o":1,"p":{"0168a431d91f25780001":"',Batch='","v":1},"t":"017cef8a4cba7f1a584b"},{"i":-1,"o":1,"p":{"v":1},"t":"017cef8a4cba82acf55e"},{"i":-1,"o":1,"p":{"v":1},"t":"017cef8a4cba87dd0196"},{"i":-1,"o":1,"p":{"01621f6ab58c2f884654":22000,"01621f6ab6ac89348f20":21200,"v":1},"t":"017cef8a4cba88a0f578"},{"i":-1,"o":1,"p":{"0168a431d91f25780001":"',BatchIdentifyingPlant='","v":1},"t":"017cef8a4cba8df32ddc"},{"i":-1,"o":1,"p":{"ff023000000000000011":"Descender output","v":1},"t":"017cef8a4cba911a5698"},{"i":-1,"o":1,"p":{"v":1},"t":"017cef8a4cba91d4cd27"},{"i":-1,"o":1,"p":{"v":1},"t":"017cef8a4cba920bc960"},{"i":-1,"o":1,"p":{"0168a431d91f25780001":"{\"Content-Type\":\"application/json\",\"Accept\":\"application/json\"}","v":1},"t":"017cef8a4cba9a408726"},{"i":-1,"o":1,"p":{"01621f6ab58c2f884654":22500,"01621f6ab6ac89348f20":21500,"v":1},"t":"017cef8a4cba9ee23a2a"},{"i":-1,"o":1,"p":{"v":1},"t":"017cef8a4cbaa69c4154"},{"i":-1,"o":1,"p":{"v":1},"t":"017cef8a4cbaa8e200fc"},{"i":-1,"o":1,"p":{"01740c5d4ae4b520dd01":3,"ff023000000000000011":"Batch","v":1},"t":"017cef8a4cbaaad7d8a4"},{"i":-1,"o":1,"p":{"01740c5d4ae4b520dd01":0,"ff023000000000000011":"Control Flow","v":1},"t":"017cef8a4cbaabd7a89f"},{"i":-1,"o":1,"p":{"v":1},"t":"017cef8a4cbab0c9f0a8"},{"i":-1,"o":1,"p":{"0168a431d91f25780001":"')/to_BatchPlant","v":1},"t":"017cef8a4cbab2b6baf2"},{"i":-1,"o":1,"p":{"0168a431d91f25780001":"/Batch(Material='","v":1},"t":"017cef8a4cbab6d1fd10"},{"i":-1,"o":1,"p":{"01740c5d4ae4b520dd01":4,"ff023000000000000011":"cds_api_batch_srv.BatchPlantType-create","v":1},"t":"017cef8a4cbab7b6ca8c"},{"i":-1,"o":1,"p":{"ff023000000000000011":"[post] /Batch(Material='","v":1},"t":"017cef8a4cbabb627dba"},{"i":-1,"o":1,"p":{"01740c5d4ae4b520dd01":4,"ff023000000000000011":"Headers","v":1},"t":"017cef8a4cbabbf167b7"},{"i":-1,"o":1,"p":{"v":1},"t":"017cef8a4cbac130ad89"},{"i":-1,"o":1,"p":{"01621f6ab58c2f884654":23000,"01621f6ab6ac89348f20":21800,"v":1},"t":"017cef8a4cbac1e47a2d"},{"i":-1,"o":1,"p":{"v":1},"t":"017cef8a4cbac37908f8"},{"i":-1,"o":1,"p":{"v":1},"t":"017cef8a4cbac4d1f61b"},{"i":-1,"o":1,"p":{"v":1},"t":"017cef8a4cbac5c61640"},{"i":-1,"o":1,"p":{"v":1},"t":"017cef8a4cbac6a7dfce"},{"i":-1,"o":1,"p":{"v":1},"t":"017cef8a4cbaccf00ae4"},{"i":-1,"o":1,"p":{"v":1},"t":"017cef8a4cbad04ad5f4"},{"i":-1,"o":1,"p":{"ff023000000000000011":"Ascender input","v":1},"t":"017cef8a4cbad09adff7"},{"i":-1,"o":1,"p":{"v":1},"t":"017cef8a4cbad3c01100"},{"i":-1,"o":1,"p":{"v":1},"t":"017cef8a4cbad86777b2"},{"i":-1,"o":1,"p":{"v":1},"t":"017cef8a4cbadafb7dbf"},{"i":-1,"o":1,"p":{"v":1},"t":"017cef8a4cbadb96f593"},{"i":-1,"o":1,"p":{"01621f6ab58c2f884654":21500,"01621f6ab6ac89348f20":20900,"v":1},"t":"017cef8a4cbadd13a11f"},{"i":-1,"o":1,"p":{"v":1},"t":"017cef8a4cbae1730dcf"},{"i":-1,"o":1,"p":{"v":1},"t":"017cef8a4cbae2fa7dfc"},{"i":-1,"o":1,"p":{"v":1},"t":"017cef8a4cbae3c94316"},{"i":-1,"o":1,"p":{"v":1},"t":"017cef8a4cbaecbc14c2"},{"i":-1,"o":1,"p":{"v":1},"t":"017cef8a4cbaedf56f6a"},{"i":-1,"o":1,"p":{"01621f6ab58c2f884654":20500,"01621f6ab6ac89348f20":20300,"v":1},"t":"017cef8a4cbaeef3408b"},{"i":-1,"o":1,"p":{"01740c5d4ae4b520dd01":1,"ff023000000000000011":"Code","v":1},"t":"017cef8a4cbaf0e2aaf6"},{"i":-1,"o":1,"p":{"ff023000000000000011":"Descender output","v":1},"t":"017cef8a4cbaf190acbc"},{"i":-1,"o":1,"p":{"ff023000000000000011":"Descender output","v":1},"t":"017cef8a4cbaf7465734"},{"i":-1,"o":1,"p":{"v":1},"t":"017cef8a4cbaf98c1a32"},{"i":-1,"o":1,"p":{"v":1},"t":"017cef8a4cbb2c12a00b"},{"i":-1,"o":1,"p":{"ff023000000000000011":"Ascender input","v":1},"t":"017cef8a4cbbc684e5f1"},{"i":-1,"o":1,"p":{"v":1},"t":"017cef8a4cbbef63b7c9"},{"i":-1,"o":1,"p":{"01703376c4a81c0e9d91":"/Batch(Material='","01703376c4a81c0e9d92":"Add new entity to related to_BatchPlant","v":1},"t":"017cef8a5a0931578092"},{"i":-1,"o":1,"p":{"01703376c4a81c0e9d92":"-","v":1},"t":"017cef8a5a09551e9f74"},{"i":-1,"o":1,"p":{"01703376c4a81c0e9d92":"-","v":1},"t":"017cef8a5a0961736425"},{"i":-1,"o":1,"p":{"01703376c4a81c0e9d92":"-","v":1},"t":"017cef8a5a0969342387"},{"i":-1,"o":1,"p":{"01703376c4a81c0e9d92":"-","v":1},"t":"017cef8a5a097cb4c9ca"},{"i":-1,"o":1,"p":{"01703376c4a81c0e9d92":"-","v":1},"t":"017cef8a5a098e25aab7"},{"i":-1,"o":1,"p":{"01703376c4a81c0e9d92":"-","v":1},"t":"017cef8a5a09a78c2af9"},{"i":-1,"o":1,"p":{"01703376c4a81c0e9d92":"-","v":1},"t":"017cef8a5a09a9d3004b"},{"i":-1,"o":1,"p":{"01703376c4a81c0e9d92":"-","v":1},"t":"017cef8a5a09b4fdf1b4"},{"i":-1,"o":1,"p":{"01703376c4a81c0e9d92":"-","v":1},"t":"017cef8a5a09c759ec24"},{"i":-1,"o":1,"p":{"01703376c4a81c0e9d92":"-","v":1},"t":"017cef8a5a09f0ce9151"}],"optionalOperations":[],"rootTag":"017cef8a4cbabb627dba"}
