{
  "rootTag": "017aedae74ab08a83af4",
  "operations": [
    {
      "o": 4,
      "m": "ff02200000000000000u",
      "l": "017aedae74ab08a83af4",
      "r": "0179b269f70efbab6b8d",
      "i": -1
    },
    {
      "o": 4,
      "m": "01621fb84e320000f00b",
      "l": "017aedae74ab08a83af4",
      "r": "017aedafa2b34aabeb07",
      "i": -1
    },
    {
      "o": 4,
      "m": "01621fb84e320000f00b",
      "l": "017aedae74ab08a83af4",
      "r": "017aedaef7907c508091",
      "i": -1
    },
    {
      "o": 4,
      "m": "ff022000000000000000",
      "l": "017aedae74ab08a83af4",
      "r": "01621fb84e320000f011",
      "i": -1
    },
    {
      "o": 4,
      "m": "ff02200000000000000e",
      "l": "017aedae74ab08a83af4",
      "r": "0168c6f020f2a96f0000",
      "i": -1
    },
    {
      "o": 4,
      "m": "ff02200000000000000f",
      "l": "017aedae74ab08a83af4",
      "r": "017b4e2134e289423440",
      "i": -1
    },
    {
      "o": 4,
      "m": "ff02200000000000000f",
      "l": "017aedae74ab08a83af4",
      "r": "017aedaef7907c508091",
      "i": -1
    },
    {
      "o": 4,
      "m": "ff02200000000000000f",
      "l": "017aedae74ab08a83af4",
      "r": "017aedafa2b34aabeb07",
      "i": -1
    },
    {
      "o": 4,
      "m": "ff022000000000000003",
      "l": "017aedae74ab08a83af4",
      "r": "0179b269f70efbab6b8d",
      "i": -1
    },
    {
      "o": 4,
      "m": "0168a431d3b9b7438424",
      "l": "017aedafa2b34aabeb07",
      "r": "01621fb84e320000cf00",
      "i": -1
    },
    {
      "o": 4,
      "m": "ff022000000000000000",
      "l": "017aedafa2b34aabeb07",
      "r": "0168a431d25001540002",
      "i": -1
    },
    {
      "o": 4,
      "m": "ff02200000000000000f",
      "l": "017aedafa2b34aabeb07",
      "r": "017b4e213508d4b79c10",
      "i": -1
    },
    {
      "o": 4,
      "m": "ff022000000000000003",
      "l": "017aedafa2b34aabeb07",
      "r": "017aedae74ab08a83af4",
      "i": -1
    },
    {
      "o": 4,
      "m": "ff02200000000000000f",
      "l": "017aedaef7907c508091",
      "r": "017b4e21350fe85c9f37",
      "i": -1
    },
    {
      "o": 4,
      "m": "0168a431d3b9b7438424",
      "l": "017aedaef7907c508091",
      "r": "ff021000000000000011",
      "i": -1
    },
    {
      "o": 4,
      "m": "ff022000000000000000",
      "l": "017aedaef7907c508091",
      "r": "0168a431d25001540002",
      "i": -1
    },
    {
      "o": 4,
      "m": "ff022000000000000003",
      "l": "017aedaef7907c508091",
      "r": "017aedae74ab08a83af4",
      "i": -1
    },
    {
      "o": 4,
      "m": "01703376c4a81c0e9d93",
      "l": "017b4e2134e289423440",
      "r": "017aedae74ab08a83af4",
      "i": -1
    },
    {
      "o": 4,
      "m": "ff022000000000000000",
      "l": "017b4e2134e289423440",
      "r": "01703376c4a81c0e9d90",
      "i": -1
    },
    {
      "o": 4,
      "m": "ff022000000000000003",
      "l": "017b4e2134e289423440",
      "r": "017aedae74ab08a83af4",
      "i": -1
    },
    {
      "o": 4,
      "m": "01703376c4a81c0e9d93",
      "l": "017b4e213508d4b79c10",
      "r": "017aedafa2b34aabeb07",
      "i": -1
    },
    {
      "o": 4,
      "m": "ff022000000000000003",
      "l": "017b4e213508d4b79c10",
      "r": "017aedae74ab08a83af4",
      "i": -1
    },
    {
      "o": 4,
      "m": "ff022000000000000000",
      "l": "017b4e213508d4b79c10",
      "r": "01703376c4a81c0e9d90",
      "i": -1
    },
    {
      "o": 4,
      "m": "01703376c4a81c0e9d93",
      "l": "017b4e21350fe85c9f37",
      "r": "017aedaef7907c508091",
      "i": -1
    },
    {
      "o": 4,
      "m": "ff022000000000000003",
      "l": "017b4e21350fe85c9f37",
      "r": "017aedae74ab08a83af4",
      "i": -1
    },
    {
      "o": 4,
      "m": "ff022000000000000000",
      "l": "017b4e21350fe85c9f37",
      "r": "01703376c4a81c0e9d90",
      "i": -1
    }
  ],
  "optionalOperations": [
    {
      "o": 4,
      "m": "ff022000000000000003",
      "l": "017aedae74ab08a83af4",
      "r": "0179b269f70efbab6b8d",
      "i": -1
    },
    {
      "o": 4,
      "m": "ff02200000000000000u",
      "l": "017aedae74ab08a83af4",
      "r": "0179b269f70efbab6b8d",
      "i": -1
    },
    {
      "o": 4,
      "m": "ff02200000000000000f",
      "l": "0179b269f70efbab6b8d",
      "r": "017aedae74ab08a83af4",
      "i": -1
    },
    {
      "o": 4,
      "m": "016a697ef00ce7554692",
      "l": "0179b269f70efbab6b8d",
      "r": "017aedae74ab08a83af4",
      "i": -1
    }
  ]
}
