{"operations":[{"i":-1,"o":1,"p":{"01740c5d4ae4b520dd01":0,"ff023000000000000011":"Object","v":1},"t":"017de1a9a8280dff74cd"},{"i":-1,"o":1,"p":{"01621fb84e320000f001":"public","ff023000000000000011":"Get Order's attributes","v":2},"t":"017de1a9a828918a52f9"},{"i":-1,"o":1,"p":{"v":1},"t":"017de1a9a828dadb4e8d"},{"i":-1,"o":1,"p":{"ff023000000000000011":"Descender output","v":1},"t":"017de1a9a828f1d5164d"},{"i":-1,"o":1,"p":{"v":1},"t":"017de1a9a8290395c5cc"},{"i":-1,"o":1,"p":{"01740c5d4ae4b520dd01":0,"ff023000000000000011":"delivery_address_id","v":1},"t":"017de1a9a8291b60d060"},{"i":-1,"o":1,"p":{"01621f6ab58c2f884654":20000,"01621f6ab6ac89348f20":20000,"v":1},"t":"017de1a9a829210069e7"},{"i":-1,"o":1,"p":{"v":1},"t":"017de1a9a8292aaa6f80"},{"i":-1,"o":1,"p":{"v":1},"t":"017de1a9a8293170d59a"},{"i":-1,"o":1,"p":{"v":1},"t":"017de1a9a82932f0ae08"},{"i":-1,"o":1,"p":{"01740c5d4ae4b520dd01":1,"ff023000000000000011":"billing_address_id","v":1},"t":"017de1a9a82950c7dfae"},{"i":-1,"o":1,"p":{"ff023000000000000011":"Ascender input","v":1},"t":"017de1a9a829582fa8d3"},{"i":-1,"o":1,"p":{"v":1},"t":"017de1a9a8298af819f0"},{"i":-1,"o":1,"p":{"v":1},"t":"017de1a9a82999d20664"},{"i":-1,"o":1,"p":{"v":1},"t":"017de1a9a829a7117ccb"},{"i":-1,"o":1,"p":{"v":1},"t":"017de1a9a829af5b522f"},{"i":-1,"o":1,"p":{"v":2},"t":"017de1a9a829b54c5851"},{"i":-1,"o":1,"p":{"v":1},"t":"017de1a9a829d3fd6d0e"},{"i":-1,"o":1,"p":{"01621f6ab58c2f884654":20250,"01621f6ab6ac89348f20":20150,"v":1},"t":"017de1a9a829f3dfb27a"},{"i":-1,"o":1,"p":{"ff023000000000000011":"Ascender input","v":1},"t":"017de1a9a829ffc86359"},{"i":-1,"o":1,"p":{"v":1},"t":"017de1a9a82a0685b79d"},{"i":-1,"o":1,"p":{"v":1},"t":"017de1a9a82a155d6d51"},{"i":-1,"o":1,"p":{"01740c5d4ae4b520dd01":2,"ff023000000000000011":"bp_id","v":1},"t":"017de1a9a82a15ad5f94"},{"i":-1,"o":1,"p":{"01740c5d4ae4b520dd01":4,"ff023000000000000011":"order_id","v":1},"t":"017de1a9a82a17b628d3"},{"i":-1,"o":1,"p":{"v":1},"t":"017de1a9a82a1bdab403"},{"i":-1,"o":1,"p":{"v":1},"t":"017de1a9a82a20bdab07"},{"i":-1,"o":1,"p":{"v":1},"t":"017de1a9a82a2899f7a5"},{"i":-1,"o":1,"p":{"v":1},"t":"017de1a9a82a2ec3a52f"},{"i":-1,"o":1,"p":{"v":2},"t":"017de1a9a82a30166b8b"},{"i":-1,"o":1,"p":{"01621f6ab58c2f884654":21000,"01621f6ab6ac89348f20":20600,"v":1},"t":"017de1a9a82a353fe93c"},{"i":-1,"o":1,"p":{"01621f6ab58c2f884654":20500,"01621f6ab6ac89348f20":20300,"v":1},"t":"017de1a9a82a3b8dae0c"},{"i":-1,"o":1,"p":{"v":1},"t":"017de1a9a82a4122d46b"},{"i":-1,"o":1,"p":{"v":1},"t":"017de1a9a82a48643d11"},{"i":-1,"o":1,"p":{"v":1},"t":"017de1a9a82a49c652b8"},{"i":-1,"o":1,"p":{"v":1},"t":"017de1a9a82a56e97c11"},{"i":-1,"o":1,"p":{"v":1},"t":"017de1a9a82a5c2eda8a"},{"i":-1,"o":1,"p":{"v":1},"t":"017de1a9a82a62b2b5df"},{"i":-1,"o":1,"p":{"v":1},"t":"017de1a9a82a77c688d7"},{"i":-1,"o":1,"p":{"v":1},"t":"017de1a9a82a793b79e4"},{"i":-1,"o":1,"p":{"v":1},"t":"017de1a9a82a7dec9817"},{"i":-1,"o":1,"p":{"01740c5d4ae4b520dd01":5,"ff023000000000000011":"creation_date","v":1},"t":"017de1a9a82a81b4b72a"},{"i":-1,"o":1,"p":{"v":1},"t":"017de1a9a82a861fd089"},{"i":-1,"o":1,"p":{"ff023000000000000011":"Ascender input","v":1},"t":"017de1a9a82a8bb39769"},{"i":-1,"o":1,"p":{"v":1},"t":"017de1a9a82a9879296d"},{"i":-1,"o":1,"p":{"v":2},"t":"017de1a9a82a9e8e5a18"},{"i":-1,"o":1,"p":{"v":1},"t":"017de1a9a82aa037efb9"},{"i":-1,"o":1,"p":{"v":2},"t":"017de1a9a82aa1eb0eb6"},{"i":-1,"o":1,"p":{"ff023000000000000011":"Ascender input","v":1},"t":"017de1a9a82abb8d71ae"},{"i":-1,"o":1,"p":{"v":1},"t":"017de1a9a82abd4c5329"},{"i":-1,"o":1,"p":{"01621f6ab58c2f884654":20750,"01621f6ab6ac89348f20":20450,"v":1},"t":"017de1a9a82abfe71c0c"},{"i":-1,"o":1,"p":{"v":1},"t":"017de1a9a82acb1d3045"},{"i":-1,"o":1,"p":{"01621f6ab58c2f884654":21250,"01621f6ab6ac89348f20":20750,"v":1},"t":"017de1a9a82acb7f99c8"},{"i":-1,"o":1,"p":{"01740c5d4ae4b520dd01":6,"ff023000000000000011":"total price","v":1},"t":"017de1a9a82acbc084a2"},{"i":-1,"o":1,"p":{"ff023000000000000011":"Ascender input","v":1},"t":"017de1a9a82acdd58635"},{"i":-1,"o":1,"p":{"ff023000000000000011":"Ascender input","v":1},"t":"017de1a9a82ace48a3d5"},{"i":-1,"o":1,"p":{"v":1},"t":"017de1a9a82ad226d30a"},{"i":-1,"o":1,"p":{"v":2},"t":"017de1a9a82ad2abf3ce"},{"i":-1,"o":1,"p":{"v":1},"t":"017de1a9a82adb3b01e6"},{"i":-1,"o":1,"p":{"v":2},"t":"017de1a9a82adf944969"},{"i":-1,"o":1,"p":{"v":1},"t":"017de1a9a82ae28c6ef3"},{"i":-1,"o":1,"p":{"01621f6ab58c2f884654":21500,"01621f6ab6ac89348f20":20900,"v":1},"t":"017de1a9a82ae3133de8"},{"i":-1,"o":1,"p":{"ff023000000000000011":"Ascender input","v":1},"t":"017de1a9a82aee1d1af3"},{"i":-1,"o":1,"p":{"01740c5d4ae4b520dd01":3,"ff023000000000000011":"delivery_date_expected","v":1},"t":"017de1a9a82af6eed86b"},{"i":-1,"o":1,"p":{"v":1},"t":"017de1a9a82af93e4296"},{"i":-1,"o":1,"p":{"01621f6ab58c2f884654":22000,"01621f6ab6ac89348f20":21200,"v":1},"t":"017de1a9a82b016cdeaa"},{"i":-1,"o":1,"p":{"v":1},"t":"017de1a9a82b01b3a1c8"},{"i":-1,"o":1,"p":{"01621f6ab58c2f884654":21750,"01621f6ab6ac89348f20":21050,"v":1},"t":"017de1a9a82b046e8471"},{"i":-1,"o":1,"p":{"ff023000000000000011":"Ascender input","v":1},"t":"017de1a9a82b0d054eda"},{"i":-1,"o":1,"p":{"01740c5d4ae4b520dd01":7,"ff023000000000000011":"status","v":1},"t":"017de1a9a82b0e5181f1"},{"i":-1,"o":1,"p":{"v":1},"t":"017de1a9a82b0ea442ad"},{"i":-1,"o":1,"p":{"v":1},"t":"017de1a9a82b14d3be9e"},{"i":-1,"o":1,"p":{"v":1},"t":"017de1a9a82b23dacc99"},{"i":-1,"o":1,"p":{"v":2},"t":"017de1a9a82b45f6595e"},{"i":-1,"o":1,"p":{"v":1},"t":"017de1a9a82b5930410d"},{"i":-1,"o":1,"p":{"v":1},"t":"017de1a9a82b5fb5d976"},{"i":-1,"o":1,"p":{"v":1},"t":"017de1a9a82b6f609768"},{"i":-1,"o":1,"p":{"v":1},"t":"017de1a9a82b7498a918"},{"i":-1,"o":1,"p":{"v":1},"t":"017de1a9a82b813a4f94"},{"i":-1,"o":1,"p":{"v":2},"t":"017de1a9a82b9059460b"},{"i":-1,"o":1,"p":{"01740c5d4ae4b520dd01":8,"ff023000000000000011":"name","v":1},"t":"017de1a9a82bb2c19b47"},{"i":-1,"o":1,"p":{"v":1},"t":"017de1a9a82bd2ea93e0"},{"i":-1,"o":1,"p":{"v":2},"t":"017de1a9a82bd51d6704"},{"i":-1,"o":1,"p":{"ff023000000000000011":"Ascender input","v":1},"t":"017de1a9a82bdc56bf7a"},{"i":-1,"o":1,"p":{"v":1},"t":"017de1a9a82be0fd0ca7"},{"i":-1,"o":1,"p":{"v":1},"t":"017de1a9a82beb22e1c9"}],"optionalOperations":[],"rootTag":"017de1a9a828918a52f9"}
